dh_common/__init__.py
dh_common/datetime.py
dh_common/enum.py
dh_common/http.py
dh_common/loggers.py
dh_common/math.py
dh_common/random.py
dh_common/token.py
common_tool-0.0.1.dist-info/LICENSE
common_tool-0.0.1.dist-info/METADATA
common_tool-0.0.1.dist-info/WHEEL
common_tool-0.0.1.dist-info/top_level.txt
common_tool-0.0.1.dist-info/RECORD
