Metadata-Version: 2.1
Name: common-tool
Version: 0.0.1
Summary: Basic toolkit packaging
Home-page: https://pypi.org/project/common-tool/
Author: donghao
Author-email: is_simple@163.com
License: MIT
Platform: UNKNOWN
License-File: LICENSE
Requires-Dist: six (>=1.15.0)
